safenet/__init__.py
safenet/app.py
safenet/authenticator.py
safenet/base_classes.py
safenet/config.py
safenet/crappyChat_reloaded_commandLine.py
safenet/dev_introspect.py
safenet/immutabledata.py
safenet/interface.py
safenet/localization.py
safenet/log_util.py
safenet/mutabledata.py
safenet/safe_app_defs.py
safenet/safe_auth_defs.py
safenet/safe_datatypes.py
safenet/safe_ffi_interface.py
safenet/safe_sysUri_defs.py
safenet/safe_utils.py
safenet/sysUri.py
safenet/compiled_binaries/libsafe_app.dll
safenet/compiled_binaries/libsafe_app.so
safenet/compiled_binaries/libsafe_app_mock.so
safenet/compiled_binaries/libsafe_authenticator.dll
safenet/compiled_binaries/libsafe_authenticator.so
safenet/compiled_binaries/libsafe_authenticator_mock.so
safenet/compiled_binaries/libsystem_uri.dll
safenet/compiled_binaries/libsystem_uri.so
safenet/compiled_binaries/python.bootstrap.cache
safenet/compiled_binaries/python.crust.config
safenet/compiled_binaries/python.routing.config
safenet/compiled_binaries/python3.bootstrap.cache
safenet/compiled_binaries/python3.crust.config
safenet/compiled_binaries/python3.routing.config
safenet/compiled_binaries/python3.safe_core.config
safenet/extracted_headers/safe_app_datatype_declarations_linux
safenet/extracted_headers/safe_app_datatype_declarations_windows
safenet/extracted_headers/safe_app_function_declarations
safenet/extracted_headers/safe_authenticator_datatype_declarations_linux
safenet/extracted_headers/safe_authenticator_datatype_declarations_windows
safenet/extracted_headers/safe_authenticator_function_declarations
safenet/extracted_headers/system_uri_function_declarations
safenet-0.0.1.dist-info/LICENSE
safenet-0.0.1.dist-info/METADATA
safenet-0.0.1.dist-info/WHEEL
safenet-0.0.1.dist-info/entry_points.txt
safenet-0.0.1.dist-info/top_level.txt
safenet-0.0.1.dist-info/RECORD
