Metadata-Version: 2.1
Name: safenet
Version: 0.0.1
Summary: Python interface to the SAFE binaries
Home-page: https://github.com/rid-dim/pySafe/tree/dev
Author: UNKNOWN
Author-email: UNKNOWN
License: GPL3
Keywords: safenetwork safenet interface
Platform: UNKNOWN
Classifier: Development Status :: 2 - Pre-Alpha
Classifier: License :: OSI Approved :: MIT License
Classifier: Programming Language :: Python :: 3.6
Requires-Dist: cffi
Requires-Dist: multihash
Requires-Dist: py-cid
Requires-Dist: requests
Requires-Dist: werkzeug
Requires-Dist: pyOpenSSL
